model_schemes/legal/__init__.py
model_schemes/legal/petition.py
model_schemes/test/__init__.py
model_schemes/test/test_petition.py
model_schemes-0.1.0.dist-info/LICENSE
model_schemes-0.1.0.dist-info/METADATA
model_schemes-0.1.0.dist-info/WHEEL
model_schemes-0.1.0.dist-info/RECORD
